SamsPrettyPrint/__init__.py
SamsPrettyPrint/__main__.py
SamsPrettyPrint/pretty_examples.py
SamsPrettyPrint/pretty_files.py
SamsPrettyPrint/pretty_print.py
samsprettyprint-2025.0.4.dist-info/METADATA
samsprettyprint-2025.0.4.dist-info/WHEEL
samsprettyprint-2025.0.4.dist-info/entry_points.txt
samsprettyprint-2025.0.4.dist-info/licenses/LICENSE
samsprettyprint-2025.0.4.dist-info/RECORD
