Metadata-Version: 2.4
Name: SamsPrettyPrint
Version: 2025.0.4
Summary: A package for formating titles/tabels/dicationaries/.. into neatly structed text.
Author-email: Samuel Ward <samuelwarda1@gmail.com>
License: MIT
License-File: LICENSE
Classifier: License :: OSI Approved :: MIT License
Classifier: Operating System :: OS Independent
Classifier: Programming Language :: Python :: 3
Requires-Python: >=3.10
